jupyter_slurm_provisioner_extension_nh/__init__.py
jupyter_slurm_provisioner_extension_nh/__main__.py
jupyter_slurm_provisioner_extension_nh/_version.py
jupyter_slurm_provisioner_extension_nh/handlers.py
jupyter_slurm_provisioner_extension_nh/labextension/package.json
jupyter_slurm_provisioner_extension_nh/labextension/static/153.7833e3aef8bd1aa004aa.js
jupyter_slurm_provisioner_extension_nh/labextension/static/747.1b3cd30ea2cfa1a2d336.js
jupyter_slurm_provisioner_extension_nh/labextension/static/remoteEntry.d82e87c3d27eb45c28c0.js
jupyter_slurm_provisioner_extension_nh/labextension/static/style.js
jupyter_slurm_provisioner_extension_nh/labextension/static/third-party-licenses.json
jupyter_slurm_provisioner_extension_nh-0.1.0.data/data/etc/jupyter/jupyter_notebook_config.d/jupyter_slurm_provisioner_extension_nh.json
jupyter_slurm_provisioner_extension_nh-0.1.0.data/data/etc/jupyter/jupyter_server_config.d/jupyter_slurm_provisioner_extension_nh.json
jupyter_slurm_provisioner_extension_nh-0.1.0.data/data/share/jupyter/labextensions/jupyter-slurm-provisioner-extension-nh/install.json
jupyter_slurm_provisioner_extension_nh-0.1.0.data/data/share/jupyter/labextensions/jupyter-slurm-provisioner-extension-nh/package.json
jupyter_slurm_provisioner_extension_nh-0.1.0.data/data/share/jupyter/labextensions/jupyter-slurm-provisioner-extension-nh/static/153.7833e3aef8bd1aa004aa.js
jupyter_slurm_provisioner_extension_nh-0.1.0.data/data/share/jupyter/labextensions/jupyter-slurm-provisioner-extension-nh/static/747.1b3cd30ea2cfa1a2d336.js
jupyter_slurm_provisioner_extension_nh-0.1.0.data/data/share/jupyter/labextensions/jupyter-slurm-provisioner-extension-nh/static/remoteEntry.d82e87c3d27eb45c28c0.js
jupyter_slurm_provisioner_extension_nh-0.1.0.data/data/share/jupyter/labextensions/jupyter-slurm-provisioner-extension-nh/static/style.js
jupyter_slurm_provisioner_extension_nh-0.1.0.dist-info/LICENSE
jupyter_slurm_provisioner_extension_nh-0.1.0.dist-info/METADATA
jupyter_slurm_provisioner_extension_nh-0.1.0.dist-info/WHEEL
jupyter_slurm_provisioner_extension_nh-0.1.0.dist-info/top_level.txt
jupyter_slurm_provisioner_extension_nh-0.1.0.dist-info/RECORD
